jre_mirror/__main__.py
jre_mirror/client.py
jre_mirror/enums.py
jre_mirror/temurin17.py
jre_mirror-0.0.9.dist-info/METADATA
jre_mirror-0.0.9.dist-info/WHEEL
jre_mirror-0.0.9.dist-info/licenses/LICENSE
jre_mirror-0.0.9.dist-info/RECORD
