Metadata-Version: 2.4
Name: jre-mirror
Version: 0.0.9
Summary: A simple tool to deploy the jre binary releases mirror.
Project-URL: Homepage, https://github.com/odys-z/JRE-Mirror
Project-URL: Issues, https://github.com/odys-z/JRE-Mirror/issues
Author-email: Ody Z <odys.zhou@gmail.com>
License: Copyright (c) 2025 Ody Z. All rights reserved.
License-File: LICENSE
Classifier: Operating System :: OS Independent
Classifier: Programming Language :: Python :: 3
Requires-Python: >=3.9
Requires-Dist: anson-py3>=0.3.8
Requires-Dist: semantics-py3>=0.4.0
Requires-Dist: typing-extensions>=4.0.0
Provides-Extra: testing
Requires-Dist: pytest; extra == 'testing'
Requires-Dist: requests; extra == 'testing'
